Workbook

Sheet Asumsi & Bobot
A1: SPK PEMILIHAN KARYAWAN BERPRESTASI — Metode Weighted Product (WP)
A2: Pengaturan Bobot Kriteria & Parameter Kebijakan Bonus
A4: KONFIGURASI BOBOT KRITERIA
A5: Kriteria | B5: Tipe | C5: Bobot Input (1–5) | D5: Bobot Ternormalisasi | E5: Pangkat WP
A6: Umur | B6: Benefit | C6: 3 | D6: =C6/SUM($C$6:$C$10) -> 0.2 | E6: =D6 -> 0.2
A7: Tingkat Pendidikan | B7: Benefit | C7: 4 | D7: =C7/SUM($C$6:$C$10) -> 0.26666667 | E7: =D7 -> 0.26666667
A8: Pengalaman Kerja | B8: Benefit | C8: 5 | D8: =C8/SUM($C$6:$C$10) -> 0.33333333 | E8: =D8 -> 0.33333333
A9: Gaji | B9: Cost | C9: 2 | D9: =C9/SUM($C$6:$C$10) -> 0.13333333 | E9: =-D9 -> -0.13333333
A10: Gender | B10: Benefit | C10: 1 | D10: =C10/SUM($C$6:$C$10) -> 0.066666667 | E10: =D10 -> 0.066666667
A12: Sel biru (kolom C) = input yang dapat diubah (nilai 1–5). Bobot akan otomatis ternormalisasi.
A14: KEBIJAKAN BONUS
A15: Ambang Batas Skor Vektor V | C15: 0.004
A16: Total Anggaran Bonus ($) | C16: 50000
A17: Ambang batas V = baris 15 kolom C | Anggaran bonus = baris 16 kolom C

Sheet Data Mentah
A1: DATA KARYAWAN (salary_data.csv)
A2: Age | B2: Gender | C2: Education Level | D2: Job Title | E2: Years of Experience | F2: Salary
A3: 32 | B3: Male | C3: Bachelor's | D3: Software Engineer | E3: 5 | F3: 90000
A4: 28 | B4: Female | C4: Master's | D4: Data Analyst | E4: 3 | F4: 65000
A5: 45 | B5: Male | C5: PhD | D5: Senior Manager | E5: 15 | F5: 150000
A6: 36 | B6: Female | C6: Bachelor's | D6: Sales Associate | E6: 7 | F6: 60000
A7: 52 | B7: Male | C7: Master's | D7: Director | E7: 20 | F7: 200000
A8: 29 | B8: Male | C8: Bachelor's | D8: Marketing Analyst | E8: 2 | F8: 55000
A9: 42 | B9: Female | C9: Master's | D9: Product Manager | E9: 12 | F9: 120000
A10: 31 | B10: Male | C10: Bachelor's | D10: Sales Manager | E10: 4 | F10: 80000
A11: 26 | B11: Female | C11: Bachelor's | D11: Marketing Coordinator | E11: 1 | F11: 45000
A12: 38 | B12: Male | C12: PhD | D12: Senior Scientist | E12: 10 | F12: 110000
A13: 29 | B13: Male | C13: Master's | D13: Software Developer | E13: 3 | F13: 75000
A14: 48 | B14: Female | C14: Bachelor's | D14: HR Manager | E14: 18 | F14: 140000
... A375: 44 | B375: Female | C375: PhD | D375: Senior Business Analyst | E375: 15 | F375: 150000

Sheet Normalisasi
A1: NORMALISASI DATA (Skala 1–10)
A2: # | B2: Job Title | C2: Age | D2: Gender | E2: Education Level | F2: Years of Exp | G2: Salary | H2: N_Age | I2: N_Edu | J2: N_Exp | K2: N_Salary | L2: N_Gender
A3: 1 | B3: ='Data Mentah'!D3 -> Software Engineer | C3: ='Data Mentah'!A3 -> 32 | D3: ='Data Mentah'!B3 -> Male | E3: ='Data Mentah'!C3 -> Bachelor's | F3: ='Data Mentah'!E3 -> 5 | G3: ='Data Mentah'!F3 -> 90000 | H3: =IF(MAX($C$3:$C$375)=MIN($C$3:$C$375),5,1+9*(C3-MIN($C$3:$C$375))/(MAX($C$3:$C$375)-MIN($C$3:$C$375))) -> 3.7 | I3: =1+9*(IF(E3="PhD",3,IF(E3="Master's",2,1))-1)/(3-1) -> 1 | J3: =IF(MAX($F$3:$F$375)=MIN($F$3:$F$375),5,1+9*(F3-MIN($F$3:$F$375))/(MAX($F$3:$F$375)-MIN($F$3:$F$375))) -> 2.8 | K3: =IF(MAX($G$3:$G$375)=MIN($G$3:$G$375),5,1+9*(G3-MIN($G$3:$G$375))/(MAX($G$3:$G$375)-MIN($G$3:$G$375))) -> 4.2319247 | L3: =1+9*(IF(D3="Female",2,IF(D3="Male",1,1.5))-1)/(2-1) -> 1
A4: 2 | B4: ='Data Mentah'!D4 -> Data Analyst | C4: ='Data Mentah'!A4 -> 28 | D4: ='Data Mentah'!B4 -> Female | E4: ='Data Mentah'!C4 -> Master's | F4: ='Data Mentah'!E4 -> 3 | G4: ='Data Mentah'!F4 -> 65000 | H4: =IF(MAX($C$3:$C$375)=MIN($C$3:$C$375),5,1+9*(C4-MIN($C$3:$C$375))/(MAX($C$3:$C$375)-MIN($C$3:$C$375))) -> 2.5 | I4: =1+9*(IF(E4="PhD",3,IF(E4="Master's",2,1))-1)/(3-1) -> 5.5 | J4: =IF(MAX($F$3:$F$375)=MIN($F$3:$F$375),5,1+9*(F4-MIN($F$3:$F$375))/(MAX($F$3:$F$375)-MIN($F$3:$F$375))) -> 2.08 | K4: =IF(MAX($G$3:$G$375)=MIN($G$3:$G$375),5,1+9*(G4-MIN($G$3:$G$375))/(MAX($G$3:$G$375)-MIN($G$3:$G$375))) -> 3.3306629 | L4: =1+9*(IF(D4="Female",2,IF(D4="Male",1,1.5))-1)/(2-1) -> 10
A5: 3 | B5: ='Data Mentah'!D5 -> Senior Manager | C5: ='Data Mentah'!A5 -> 45 | D5: ='Data Mentah'!B5 -> Male | E5: ='Data Mentah'!C5 -> PhD | F5: ='Data Mentah'!E5 -> 15 | G5: ='Data Mentah'!F5 -> 150000 | H5: =IF(MAX($C$3:$C$375)=MIN($C$3:$C$375),5,1+9*(C5-MIN($C$3:$C$375))/(MAX($C$3:$C$375)-MIN($C$3:$C$375))) -> 7.6 | I5: =1+9*(IF(E5="PhD",3,IF(E5="Master's",2,1))-1)/(3-1) -> 10 | J5: =IF(MAX($F$3:$F$375)=MIN($F$3:$F$375),5,1+9*(F5-MIN($F$3:$F$375))/(MAX($F$3:$F$375)-MIN($F$3:$F$375))) -> 6.4 | K5: =IF(MAX($G$3:$G$375)=MIN($G$3:$G$375),5,1+9*(G5-MIN($G$3:$G$375))/(MAX($G$3:$G$375)-MIN($G$3:$G$375))) -> 6.3949529 | L5: =1+9*(IF(D5="Female",2,IF(D5="Male",1,1.5))-1)/(2-1) -> 1
A6: 4 | B6: ='Data Mentah'!D6 -> Sales Associate | C6: ='Data Mentah'!A6 -> 36 | D6: ='Data Mentah'!B6 -> Female | E6: ='Data Mentah'!C6 -> Bachelor's | F6: ='Data Mentah'!E6 -> 7 | G6: ='Data Mentah'!F6 -> 60000 | H6: =IF(MAX($C$3:$C$375)=MIN($C$3:$C$375),5,1+9*(C6-MIN($C$3:$C$375))/(MAX($C$3:$C$375)-MIN($C$3:$C$375))) -> 4.9 | I6: =1+9*(IF(E6="PhD",3,IF(E6="Master's",2,1))-1)/(3-1) -> 1 | J6: =IF(MAX($F$3:$F$375)=MIN($F$3:$F$375),5,1+9*(F6-MIN($F$3:$F$375))/(MAX($F$3:$F$375)-MIN($F$3:$F$375))) -> 3.52 | K6: =IF(MAX($G$3:$G$375)=MIN($G$3:$G$375),5,1+9*(G6-MIN($G$3:$G$375))/(MAX($G$3:$G$375)-MIN($G$3:$G$375))) -> 3.1504106 | L6: =1+9*(IF(D6="Female",2,IF(D6="Male",1,1.5))-1)/(2-1) -> 10
A7: 5 | B7: ='Data Mentah'!D7 -> Director | C7: ='Data Mentah'!A7 -> 52 | D7: ='Data Mentah'!B7 -> Male | E7: ='Data Mentah'!C7 -> Master's | F7: ='Data Mentah'!E7 -> 20 | G7: ='Data Mentah'!F7 -> 200000 | H7: =IF(MAX($C$3:$C$375)=MIN($C$3:$C$375),5,1+9*(C7-MIN($C$3:$C$375))/(MAX($C$3:$C$375)-MIN($C$3:$C$375))) -> 9.7 | I7: =1+9*(IF(E7="PhD",3,IF(E7="Master's",2,1))-1)/(3-1) -> 5.5 | J7: =IF(MAX($F$3:$F$375)=MIN($F$3:$F$375),5,1+9*(F7-MIN($F$3:$F$375))/(MAX($F$3:$F$375)-MIN($F$3:$F$375))) -> 8.2 | K7: =IF(MAX($G$3:$G$375)=MIN($G$3:$G$375),5,1+9*(G7-MIN($G$3:$G$375))/(MAX($G$3:$G$375)-MIN($G$3:$G$375))) -> 8.1974765 | L7: =1+9*(IF(D7="Female",2,IF(D7="Male",1,1.5))-1)/(2-1) -> 1
A8: 6 | B8: ='Data Mentah'!D8 -> Marketing Analyst | C8: ='Data Mentah'!A8 -> 29 | D8: ='Data Mentah'!B8 -> Male | E8: ='Data Mentah'!C8 -> Bachelor's | F8: ='Data Mentah'!E8 -> 2 | G8: ='Data Mentah'!F8 -> 55000 | H8: =IF(MAX($C$3:$C$375)=MIN($C$3:$C$375),5,1+9*(C8-MIN($C$3:$C$375))/(MAX($C$3:$C$375)-MIN($C$3:$C$375))) -> 2.8 | I8: =1+9*(IF(E8="PhD",3,IF(E8="Master's",2,1))-1)/(3-1) -> 1 | J8: =IF(MAX($F$3:$F$375)=MIN($F$3:$F$375),5,1+9*(F8-MIN($F$3:$F$375))/(MAX($F$3:$F$375)-MIN($F$3:$F$375))) -> 1.72 | K8: =IF(MAX($G$3:$G$375)=MIN($G$3:$G$375),5,1+9*(G8-MIN($G$3:$G$375))/(MAX($G$3:$G$375)-MIN($G$3:$G$375))) -> 2.9701582 | L8: =1+9*(IF(D8="Female",2,IF(D8="Male",1,1.5))-1)/(2-1) -> 1
A9: 7 | B9: ='Data Mentah'!D9 -> Product Manager | C9: ='Data Mentah'!A9 -> 42 | D9: ='Data Mentah'!B9 -> Female | E9: ='Data Mentah'!C9 -> Master's | F9: ='Data Mentah'!E9 -> 12 | G9: ='Data Mentah'!F9 -> 120000 | H9: =IF(MAX($C$3:$C$375)=MIN($C$3:$C$375),5,1+9*(C9-MIN($C$3:$C$375))/(MAX($C$3:$C$375)-MIN($C$3:$C$375))) -> 6.7 | I9: =1+9*(IF(E9="PhD",3,IF(E9="Master's",2,1))-1)/(3-1) -> 5.5 | J9: =IF(MAX($F$3:$F$375)=MIN($F$3:$F$375),5,1+9*(F9-MIN($F$3:$F$375))/(MAX($F$3:$F$375)-MIN($F$3:$F$375))) -> 5.32 | K9: =IF(MAX($G$3:$G$375)=MIN($G$3:$G$375),5,1+9*(G9-MIN($G$3:$G$375))/(MAX($G$3:$G$375)-MIN($G$3:$G$375))) -> 5.3134388 | L9: =1+9*(IF(D9="Female",2,IF(D9="Male",1,1.5))-1)/(2-1) -> 10
A10: 8 | B10: ='Data Mentah'!D10 -> Sales Manager | C10: ='Data Mentah'!A10 -> 31 | D10: ='Data Mentah'!B10 -> Male | E10: ='Data Mentah'!C10 -> Bachelor's | F10: ='Data Mentah'!E10 -> 4 | G10: ='Data Mentah'!F10 -> 80000 | H10: =IF(MAX($C$3:$C$375)=MIN($C$3:$C$375),5,1+9*(C10-MIN($C$3:$C$375))/(MAX($C$3:$C$375)-MIN($C$3:$C$375))) -> 3.4 | I10: =1+9*(IF(E10="PhD",3,IF(E10="Master's",2,1))-1)/(3-1) -> 1 | J10: =IF(MAX($F$3:$F$375)=MIN($F$3:$F$375),5,1+9*(F10-MIN($F$3:$F$375))/(MAX($F$3:$F$375)-MIN($F$3:$F$375))) -> 2.44 | K10: =IF(MAX($G$3:$G$375)=MIN($G$3:$G$375),5,1+9*(G10-MIN($G$3:$G$375))/(MAX($G$3:$G$375)-MIN($G$3:$G$375))) -> 3.87142 | L10: =1+9*(IF(D10="Female",2,IF(D10="Male",1,1.5))-1)/(2-1) -> 1
A11: 9 | B11: ='Data Mentah'!D11 -> Marketing Coordinator | C11: ='Data Mentah'!A11 -> 26 | D11: ='Data Mentah'!B11 -> Female | E11: ='Data Mentah'!C11 -> Bachelor's | F11: ='Data Mentah'!E11 -> 1 | G11: ='Data Mentah'!F11 -> 45000 | H11: =IF(MAX($C$3:$C$375)=MIN($C$3:$C$375),5,1+9*(C11-MIN($C$3:$C$375))/(MAX($C$3:$C$375)-MIN($C$3:$C$375))) -> 1.9 | I11: =1+9*(IF(E11="PhD",3,IF(E11="Master's",2,1))-1)/(3-1) -> 1 | J11: =IF(MAX($F$3:$F$375)=MIN($F$3:$F$375),5,1+9*(F11-MIN($F$3:$F$375))/(MAX($F$3:$F$375)-MIN($F$3:$F$375))) -> 1.36 | K11: =IF(MAX($G$3:$G$375)=MIN($G$3:$G$375),5,1+9*(G11-MIN($G$3:$G$375))/(MAX($G$3:$G$375)-MIN($G$3:$G$375))) -> 2.6096535 | L11: =1+9*(IF(D11="Female",2,IF(D11="Male",1,1.5))-1)/(2-1) -> 10
A12: 10 | B12: ='Data Mentah'!D12 -> Senior Scientist | C12: ='Data Mentah'!A12 -> 38 | D12: ='Data Mentah'!B12 -> Male | E12: ='Data Mentah'!C12 -> PhD | F12: ='Data Mentah'!E12 -> 10 | G12: ='Data Mentah'!F12 -> 110000 | H12: =IF(MAX($C$3:$C$375)=MIN($C$3:$C$375),5,1+9*(C12-MIN($C$3:$C$375))/(MAX($C$3:$C$375)-MIN($C$3:$C$375))) -> 5.5 | I12: =1+9*(IF(E12="PhD",3,IF(E12="Master's",2,1))-1)/(3-1) -> 10 | J12: =IF(MAX($F$3:$F$375)=MIN($F$3:$F$375),5,1+9*(F12-MIN($F$3:$F$375))/(MAX($F$3:$F$375)-MIN($F$3:$F$375))) -> 4.6 | K12: =IF(MAX($G$3:$G$375)=MIN($G$3:$G$375),5,1+9*(G12-MIN($G$3:$G$375))/(MAX($G$3:$G$375)-MIN($G$3:$G$375))) -> 4.9529341 | L12: =1+9*(IF(D12="Female",2,IF(D12="Male",1,1.5))-1)/(2-1) -> 1
A13: 11 | B13: ='Data Mentah'!D13 -> Software Developer | C13: ='Data Mentah'!A13 -> 29 | D13: ='Data Mentah'!B13 -> Male | E13: ='Data Mentah'!C13 -> Master's | F13: ='Data Mentah'!E13 -> 3 | G13: ='Data Mentah'!F13 -> 75000 | H13: =IF(MAX($C$3:$C$375)=MIN($C$3:$C$375),5,1+9*(C13-MIN($C$3:$C$375))/(MAX($C$3:$C$375)-MIN($C$3:$C$375))) -> 2.8 | I13: =1+9*(IF(E13="PhD",3,IF(E13="Master's",2,1))-1)/(3-1) -> 5.5 | J13: =IF(MAX($F$3:$F$375)=MIN($F$3:$F$375),5,1+9*(F13-MIN($F$3:$F$375))/(MAX($F$3:$F$375)-MIN($F$3:$F$375))) -> 2.08 | K13: =IF(MAX($G$3:$G$375)=MIN($G$3:$G$375),5,1+9*(G13-MIN($G$3:$G$375))/(MAX($G$3:$G$375)-MIN($G$3:$G$375))) -> 3.6911676 | L13: =1+9*(IF(D13="Female",2,IF(D13="Male",1,1.5))-1)/(2-1) -> 1
A14: 12 | B14: ='Data Mentah'!D14 -> HR Manager | C14: ='Data Mentah'!A14 -> 48 | D14: ='Data Mentah'!B14 -> Female | E14: ='Data Mentah'!C14 -> Bachelor's | F14: ='Data Mentah'!E14 -> 18 | G14: ='Data Mentah'!F14 -> 140000 | H14: =IF(MAX($C$3:$C$375)=MIN($C$3:$C$375),5,1+9*(C14-MIN($C$3:$C$375))/(MAX($C$3:$C$375)-MIN($C$3:$C$375))) -> 8.5 | I14: =1+9*(IF(E14="PhD",3,IF(E14="Master's",2,1))-1)/(3-1) -> 1 | J14: =IF(MAX($F$3:$F$375)=MIN($F$3:$F$375),5,1+9*(F14-MIN($F$3:$F$375))/(MAX($F$3:$F$375)-MIN($F$3:$F$375))) -> 7.48 | K14: =IF(MAX($G$3:$G$375)=MIN($G$3:$G$375),5,1+9*(G14-MIN($G$3:$G$375))/(MAX($G$3:$G$375)-MIN($G$3:$G$375))) -> 6.0344482 | L14: =1+9*(IF(D14="Female",2,IF(D14="Male",1,1.5))-1)/(2-1) -> 10
... A375: 373 | B375: ='Data Mentah'!D375 -> Senior Business Analyst | C375: ='Data Mentah'!A375 -> 44 | D375: ='Data Mentah'!B375 -> Female | E375: ='Data Mentah'!C375 -> PhD | F375: ='Data Mentah'!E375 -> 15 | G375: ='Data Mentah'!F375 -> 150000 | H375: =IF(MAX($C$3:$C$375)=MIN($C$3:$C$375),5,1+9*(C375-MIN($C$3:$C$375))/(MAX($C$3:$C$375)-MIN($C$3:$C$375))) -> 7.3 | I375: =1+9*(IF(E375="PhD",3,IF(E375="Master's",2,1))-1)/(3-1) -> 10 | J375: =IF(MAX($F$3:$F$375)=MIN($F$3:$F$375),5,1+9*(F375-MIN($F$3:$F$375))/(MAX($F$3:$F$375)-MIN($F$3:$F$375))) -> 6.4 | K375: =IF(MAX($G$3:$G$375)=MIN($G$3:$G$375),5,1+9*(G375-MIN($G$3:$G$375))/(MAX($G$3:$G$375)-MIN($G$3:$G$375))) -> 6.3949529 | L375: =1+9*(IF(D375="Female",2,IF(D375="Male",1,1.5))-1)/(2-1) -> 10

Sheet Vektor S & V
A1: PERHITUNGAN VEKTOR S DAN VEKTOR V (Weighted Product)
A2: # | B2: Job Title | C2: N_Age | D2: N_Edu | E2: N_Exp | F2: N_Salary | G2: N_Gender | H2: Vektor S | I2: Vektor V | J2: Rank
A3: 1 | B3: =Normalisasi!B3 -> Software Engineer | C3: =Normalisasi!H3 -> 3.7 | D3: =Normalisasi!I3 -> 1 | E3: =Normalisasi!J3 -> 2.8 | F3: =Normalisasi!K3 -> 4.2319247 | G3: =Normalisasi!L3 -> 1 | H3: =MAX(C3,0.000000001)^'Asumsi & Bobot'!$E$6*MAX(D3,0.000000001)^'Asumsi & Bobot'!$E$7*MAX(E3,0.000000001)^'Asumsi & Bobot'!$E$8*MAX(F3,0.000000001)^'Asumsi & Bobot'!$E$9*MAX(G3,0.000000001)^'Asumsi & Bobot'!$E$10 -> 1.5106179 | I3: =H3/SUM($H$3:$H$375) -> 0.0015607645 | J3: =RANK(I3,$I$3:$I$375,0) -> 317
A4: 2 | B4: =Normalisasi!B4 -> Data Analyst | C4: =Normalisasi!H4 -> 2.5 | D4: =Normalisasi!I4 -> 5.5 | E4: =Normalisasi!J4 -> 2.08 | F4: =Normalisasi!K4 -> 3.3306629 | G4: =Normalisasi!L4 -> 10 | H4: =MAX(C4,0.000000001)^'Asumsi & Bobot'!$E$6*MAX(D4,0.000000001)^'Asumsi & Bobot'!$E$7*MAX(E4,0.000000001)^'Asumsi & Bobot'!$E$8*MAX(F4,0.000000001)^'Asumsi & Bobot'!$E$9*MAX(G4,0.000000001)^'Asumsi & Bobot'!$E$10 -> 2.3990267 | I4: =H4/SUM($H$3:$H$375) -> 0.002478665 | J4: =RANK(I4,$I$3:$I$375,0) -> 159
A5: 3 | B5: =Normalisasi!B5 -> Senior Manager | C5: =Normalisasi!H5 -> 7.6 | D5: =Normalisasi!I5 -> 10 | E5: =Normalisasi!J5 -> 6.4 | F5: =Normalisasi!K5 -> 6.3949529 | G5: =Normalisasi!L5 -> 1 | H5: =MAX(C5,0.000000001)^'Asumsi & Bobot'!$E$6*MAX(D5,0.000000001)^'Asumsi & Bobot'!$E$7*MAX(E5,0.000000001)^'Asumsi & Bobot'!$E$8*MAX(F5,0.000000001)^'Asumsi & Bobot'!$E$9*MAX(G5,0.000000001)^'Asumsi & Bobot'!$E$10 -> 4.0189357 | I5: =H5/SUM($H$3:$H$375) -> 0.0041523488 | J5: =RANK(I5,$I$3:$I$375,0) -> 62
A6: 4 | B6: =Normalisasi!B6 -> Sales Associate | C6: =Normalisasi!H6 -> 4.9 | D6: =Normalisasi!I6 -> 1 | E6: =Normalisasi!J6 -> 3.52 | F6: =Normalisasi!K6 -> 3.1504106 | G6: =Normalisasi!L6 -> 10 | H6: =MAX(C6,0.000000001)^'Asumsi & Bobot'!$E$6*MAX(D6,0.000000001)^'Asumsi & Bobot'!$E$7*MAX(E6,0.000000001)^'Asumsi & Bobot'!$E$8*MAX(F6,0.000000001)^'Asumsi & Bobot'!$E$9*MAX(G6,0.000000001)^'Asumsi & Bobot'!$E$10 -> 2.0914034 | I6: =H6/SUM($H$3:$H$375) -> 0.0021608299 | J6: =RANK(I6,$I$3:$I$375,0) -> 203
A7: 5 | B7: =Normalisasi!B7 -> Director | C7: =Normalisasi!H7 -> 9.7 | D7: =Normalisasi!I7 -> 5.5 | E7: =Normalisasi!J7 -> 8.2 | F7: =Normalisasi!K7 -> 8.1974765 | G7: =Normalisasi!L7 -> 1 | H7: =MAX(C7,0.000000001)^'Asumsi & Bobot'!$E$6*MAX(D7,0.000000001)^'Asumsi & Bobot'!$E$7*MAX(E7,0.000000001)^'Asumsi & Bobot'!$E$8*MAX(F7,0.000000001)^'Asumsi & Bobot'!$E$9*MAX(G7,0.000000001)^'Asumsi & Bobot'!$E$10 -> 3.7806371 | I7: =H7/SUM($H$3:$H$375) -> 0.0039061395 | J7: =RANK(I7,$I$3:$I$375,0) -> 80
A8: 6 | B8: =Normalisasi!B8 -> Marketing Analyst | C8: =Normalisasi!H8 -> 2.8 | D8: =Normalisasi!I8 -> 1 | E8: =Normalisasi!J8 -> 1.72 | F8: =Normalisasi!K8 -> 2.9701582 | G8: =Normalisasi!L8 -> 1 | H8: =MAX(C8,0.000000001)^'Asumsi & Bobot'!$E$6*MAX(D8,0.000000001)^'Asumsi & Bobot'!$E$7*MAX(E8,0.000000001)^'Asumsi & Bobot'!$E$8*MAX(F8,0.000000001)^'Asumsi & Bobot'!$E$9*MAX(G8,0.000000001)^'Asumsi & Bobot'!$E$10 -> 1.2732211 | I8: =H8/SUM($H$3:$H$375) -> 0.001315487 | J8: =RANK(I8,$I$3:$I$375,0) -> 356
A9: 7 | B9: =Normalisasi!B9 -> Product Manager | C9: =Normalisasi!H9 -> 6.7 | D9: =Normalisasi!I9 -> 5.5 | E9: =Normalisasi!J9 -> 5.32 | F9: =Normalisasi!K9 -> 5.3134388 | G9: =Normalisasi!L9 -> 10 | H9: =MAX(C9,0.000000001)^'Asumsi & Bobot'!$E$6*MAX(D9,0.000000001)^'Asumsi & Bobot'!$E$7*MAX(E9,0.000000001)^'Asumsi & Bobot'!$E$8*MAX(F9,0.000000001)^'Asumsi & Bobot'!$E$9*MAX(G9,0.000000001)^'Asumsi & Bobot'!$E$10 -> 3.7546155 | I9: =H9/SUM($H$3:$H$375) -> 0.0038792541 | J9: =RANK(I9,$I$3:$I$375,0) -> 84
A10: 8 | B10: =Normalisasi!B10 -> Sales Manager | C10: =Normalisasi!H10 -> 3.4 | D10: =Normalisasi!I10 -> 1 | E10: =Normalisasi!J10 -> 2.44 | F10: =Normalisasi!K10 -> 3.87142 | G10: =Normalisasi!L10 -> 1 | H10: =MAX(C10,0.000000001)^'Asumsi & Bobot'!$E$6*MAX(D10,0.000000001)^'Asumsi & Bobot'!$E$7*MAX(E10,0.000000001)^'Asumsi & Bobot'!$E$8*MAX(F10,0.000000001)^'Asumsi & Bobot'!$E$9*MAX(G10,0.000000001)^'Asumsi & Bobot'!$E$10 -> 1.4356316 | I10: =H10/SUM($H$3:$H$375) -> 0.001483289 | J10: =RANK(I10,$I$3:$I$375,0) -> 328
A11: 9 | B11: =Normalisasi!B11 -> Marketing Coordinator | C11: =Normalisasi!H11 -> 1.9 | D11: =Normalisasi!I11 -> 1 | E11: =Normalisasi!J11 -> 1.36 | F11: =Normalisasi!K11 -> 2.6096535 | G11: =Normalisasi!L11 -> 10 | H11: =MAX(C11,0.000000001)^'Asumsi & Bobot'!$E$6*MAX(D11,0.000000001)^'Asumsi & Bobot'!$E$7*MAX(E11,0.000000001)^'Asumsi & Bobot'!$E$8*MAX(F11,0.000000001)^'Asumsi & Bobot'!$E$9*MAX(G11,0.000000001)^'Asumsi & Bobot'!$E$10 -> 1.2923673 | I11: =H11/SUM($H$3:$H$375) -> 0.0013352689 | J11: =RANK(I11,$I$3:$I$375,0) -> 346
A12: 10 | B12: =Normalisasi!B12 -> Senior Scientist | C12: =Normalisasi!H12 -> 5.5 | D12: =Normalisasi!I12 -> 10 | E12: =Normalisasi!J12 -> 4.6 | F12: =Normalisasi!K12 -> 4.9529341 | G12: =Normalisasi!L12 -> 1 | H12: =MAX(C12,0.000000001)^'Asumsi & Bobot'!$E$6*MAX(D12,0.000000001)^'Asumsi & Bobot'!$E$7*MAX(E12,0.000000001)^'Asumsi & Bobot'!$E$8*MAX(F12,0.000000001)^'Asumsi & Bobot'!$E$9*MAX(G12,0.000000001)^'Asumsi & Bobot'!$E$10 -> 3.4914847 | I12: =H12/SUM($H$3:$H$375) -> 0.0036073884 | J12: =RANK(I12,$I$3:$I$375,0) -> 109
A13: 11 | B13: =Normalisasi!B13 -> Software Developer | C13: =Normalisasi!H13 -> 2.8 | D13: =Normalisasi!I13 -> 5.5 | E13: =Normalisasi!J13 -> 2.08 | F13: =Normalisasi!K13 -> 3.6911676 | G13: =Normalisasi!L13 -> 1 | H13: =MAX(C13,0.000000001)^'Asumsi & Bobot'!$E$6*MAX(D13,0.000000001)^'Asumsi & Bobot'!$E$7*MAX(E13,0.000000001)^'Asumsi & Bobot'!$E$8*MAX(F13,0.000000001)^'Asumsi & Bobot'!$E$9*MAX(G13,0.000000001)^'Asumsi & Bobot'!$E$10 -> 2.0761605 | I13: =H13/SUM($H$3:$H$375) -> 0.002145081 | J13: =RANK(I13,$I$3:$I$375,0) -> 205
A14: 12 | B14: =Normalisasi!B14 -> HR Manager | C14: =Normalisasi!H14 -> 8.5 | D14: =Normalisasi!I14 -> 1 | E14: =Normalisasi!J14 -> 7.48 | F14: =Normalisasi!K14 -> 6.0344482 | G14: =Normalisasi!L14 -> 10 | H14: =MAX(C14,0.000000001)^'Asumsi & Bobot'!$E$6*MAX(D14,0.000000001)^'Asumsi & Bobot'!$E$7*MAX(E14,0.000000001)^'Asumsi & Bobot'!$E$8*MAX(F14,0.000000001)^'Asumsi & Bobot'!$E$9*MAX(G14,0.000000001)^'Asumsi & Bobot'!$E$10 -> 2.752745 | I14: =H14/SUM($H$3:$H$375) -> 0.0028441254 | J14: =RANK(I14,$I$3:$I$375,0) -> 136
... A375: 373 | B375: =Normalisasi!B375 -> Senior Business Analyst | C375: =Normalisasi!H375 -> 7.3 | D375: =Normalisasi!I375 -> 10 | E375: =Normalisasi!J375 -> 6.4 | F375: =Normalisasi!K375 -> 6.3949529 | G375: =Normalisasi!L375 -> 10 | H375: =MAX(C375,0.000000001)^'Asumsi & Bobot'!$E$6*MAX(D375,0.000000001)^'Asumsi & Bobot'!$E$7*MAX(E375,0.000000001)^'Asumsi & Bobot'!$E$8*MAX(F375,0.000000001)^'Asumsi & Bobot'!$E$9*MAX(G375,0.000000001)^'Asumsi & Bobot'!$E$10 -> 4.6481441 | I375: =H375/SUM($H$3:$H$375) -> 0.0048024444 | J375: =RANK(I375,$I$3:$I$375,0) -> 21

Sheet Hasil & Bonus
A1: HASIL KEPUTUSAN & DISTRIBUSI BONUS PROPORSIONAL
A2: Rank | B2: Job Title | C2: Education | D2: Exp (yr) | E2: Salary | F2: Vektor V | G2: Status Keputusan | H2: Bagian V Penerima | I2: Nilai Bonus ($)
A3: ='Vektor S & V'!J3 -> 317 | B3: ='Vektor S & V'!B3 -> Software Engineer | C3: ='Data Mentah'!C3 -> Bachelor's | D3: ='Data Mentah'!E3 -> 5 | E3: ='Data Mentah'!F3 -> 90000 | F3: ='Vektor S & V'!I3 -> 0.0015607645 | G3: =IF(F3>='Asumsi & Bobot'!$C$15,"Mendapat Bonus","Tidak Mendapat Bonus") -> Tidak Mendapat Bonus | H3: =IF(G3="Mendapat Bonus",F3/(SUMIF($G$3:$G$375,"Mendapat Bonus",$F$3:$F$375)),0) -> 0 | I3: =IF(G3="Mendapat Bonus",H3*'Asumsi & Bobot'!$C$16,0) -> 0
A4: ='Vektor S & V'!J4 -> 159 | B4: ='Vektor S & V'!B4 -> Data Analyst | C4: ='Data Mentah'!C4 -> Master's | D4: ='Data Mentah'!E4 -> 3 | E4: ='Data Mentah'!F4 -> 65000 | F4: ='Vektor S & V'!I4 -> 0.002478665 | G4: =IF(F4>='Asumsi & Bobot'!$C$15,"Mendapat Bonus","Tidak Mendapat Bonus") -> Tidak Mendapat Bonus | H4: =IF(G4="Mendapat Bonus",F4/(SUMIF($G$3:$G$375,"Mendapat Bonus",$F$3:$F$375)),0) -> 0 | I4: =IF(G4="Mendapat Bonus",H4*'Asumsi & Bobot'!$C$16,0) -> 0
A5: ='Vektor S & V'!J5 -> 62 | B5: ='Vektor S & V'!B5 -> Senior Manager | C5: ='Data Mentah'!C5 -> PhD | D5: ='Data Mentah'!E5 -> 15 | E5: ='Data Mentah'!F5 -> 150000 | F5: ='Vektor S & V'!I5 -> 0.0041523488 | G5: =IF(F5>='Asumsi & Bobot'!$C$15,"Mendapat Bonus","Tidak Mendapat Bonus") -> Mendapat Bonus | H5: =IF(G5="Mendapat Bonus",F5/(SUMIF($G$3:$G$375,"Mendapat Bonus",$F$3:$F$375)),0) -> 0.012563915 | I5: =IF(G5="Mendapat Bonus",H5*'Asumsi & Bobot'!$C$16,0) -> 628.19575
A6: ='Vektor S & V'!J6 -> 203 | B6: ='Vektor S & V'!B6 -> Sales Associate | C6: ='Data Mentah'!C6 -> Bachelor's | D6: ='Data Mentah'!E6 -> 7 | E6: ='Data Mentah'!F6 -> 60000 | F6: ='Vektor S & V'!I6 -> 0.0021608299 | G6: =IF(F6>='Asumsi & Bobot'!$C$15,"Mendapat Bonus","Tidak Mendapat Bonus") -> Tidak Mendapat Bonus | H6: =IF(G6="Mendapat Bonus",F6/(SUMIF($G$3:$G$375,"Mendapat Bonus",$F$3:$F$375)),0) -> 0 | I6: =IF(G6="Mendapat Bonus",H6*'Asumsi & Bobot'!$C$16,0) -> 0
A7: ='Vektor S & V'!J7 -> 80 | B7: ='Vektor S & V'!B7 -> Director | C7: ='Data Mentah'!C7 -> Master's | D7: ='Data Mentah'!E7 -> 20 | E7: ='Data Mentah'!F7 -> 200000 | F7: ='Vektor S & V'!I7 -> 0.0039061395 | G7: =IF(F7>='Asumsi & Bobot'!$C$15,"Mendapat Bonus","Tidak Mendapat Bonus") -> Tidak Mendapat Bonus | H7: =IF(G7="Mendapat Bonus",F7/(SUMIF($G$3:$G$375,"Mendapat Bonus",$F$3:$F$375)),0) -> 0 | I7: =IF(G7="Mendapat Bonus",H7*'Asumsi & Bobot'!$C$16,0) -> 0
A8: ='Vektor S & V'!J8 -> 356 | B8: ='Vektor S & V'!B8 -> Marketing Analyst | C8: ='Data Mentah'!C8 -> Bachelor's | D8: ='Data Mentah'!E8 -> 2 | E8: ='Data Mentah'!F8 -> 55000 | F8: ='Vektor S & V'!I8 -> 0.001315487 | G8: =IF(F8>='Asumsi & Bobot'!$C$15,"Mendapat Bonus","Tidak Mendapat Bonus") -> Tidak Mendapat Bonus | H8: =IF(G8="Mendapat Bonus",F8/(SUMIF($G$3:$G$375,"Mendapat Bonus",$F$3:$F$375)),0) -> 0 | I8: =IF(G8="Mendapat Bonus",H8*'Asumsi & Bobot'!$C$16,0) -> 0
A9: ='Vektor S & V'!J9 -> 84 | B9: ='Vektor S & V'!B9 -> Product Manager | C9: ='Data Mentah'!C9 -> Master's | D9: ='Data Mentah'!E9 -> 12 | E9: ='Data Mentah'!F9 -> 120000 | F9: ='Vektor S & V'!I9 -> 0.0038792541 | G9: =IF(F9>='Asumsi & Bobot'!$C$15,"Mendapat Bonus","Tidak Mendapat Bonus") -> Tidak Mendapat Bonus | H9: =IF(G9="Mendapat Bonus",F9/(SUMIF($G$3:$G$375,"Mendapat Bonus",$F$3:$F$375)),0) -> 0 | I9: =IF(G9="Mendapat Bonus",H9*'Asumsi & Bobot'!$C$16,0) -> 0
A10: ='Vektor S & V'!J10 -> 328 | B10: ='Vektor S & V'!B10 -> Sales Manager | C10: ='Data Mentah'!C10 -> Bachelor's | D10: ='Data Mentah'!E10 -> 4 | E10: ='Data Mentah'!F10 -> 80000 | F10: ='Vektor S & V'!I10 -> 0.001483289 | G10: =IF(F10>='Asumsi & Bobot'!$C$15,"Mendapat Bonus","Tidak Mendapat Bonus") -> Tidak Mendapat Bonus | H10: =IF(G10="Mendapat Bonus",F10/(SUMIF($G$3:$G$375,"Mendapat Bonus",$F$3:$F$375)),0) -> 0 | I10: =IF(G10="Mendapat Bonus",H10*'Asumsi & Bobot'!$C$16,0) -> 0
A11: ='Vektor S & V'!J11 -> 346 | B11: ='Vektor S & V'!B11 -> Marketing Coordinator | C11: ='Data Mentah'!C11 -> Bachelor's | D11: ='Data Mentah'!E11 -> 1 | E11: ='Data Mentah'!F11 -> 45000 | F11: ='Vektor S & V'!I11 -> 0.0013352689 | G11: =IF(F11>='Asumsi & Bobot'!$C$15,"Mendapat Bonus","Tidak Mendapat Bonus") -> Tidak Mendapat Bonus | H11: =IF(G11="Mendapat Bonus",F11/(SUMIF($G$3:$G$375,"Mendapat Bonus",$F$3:$F$375)),0) -> 0 | I11: =IF(G11="Mendapat Bonus",H11*'Asumsi & Bobot'!$C$16,0) -> 0
A12: ='Vektor S & V'!J12 -> 109 | B12: ='Vektor S & V'!B12 -> Senior Scientist | C12: ='Data Mentah'!C12 -> PhD | D12: ='Data Mentah'!E12 -> 10 | E12: ='Data Mentah'!F12 -> 110000 | F12: ='Vektor S & V'!I12 -> 0.0036073884 | G12: =IF(F12>='Asumsi & Bobot'!$C$15,"Mendapat Bonus","Tidak Mendapat Bonus") -> Tidak Mendapat Bonus | H12: =IF(G12="Mendapat Bonus",F12/(SUMIF($G$3:$G$375,"Mendapat Bonus",$F$3:$F$375)),0) -> 0 | I12: =IF(G12="Mendapat Bonus",H12*'Asumsi & Bobot'!$C$16,0) -> 0
A13: ='Vektor S & V'!J13 -> 205 | B13: ='Vektor S & V'!B13 -> Software Developer | C13: ='Data Mentah'!C13 -> Master's | D13: ='Data Mentah'!E13 -> 3 | E13: ='Data Mentah'!F13 -> 75000 | F13: ='Vektor S & V'!I13 -> 0.002145081 | G13: =IF(F13>='Asumsi & Bobot'!$C$15,"Mendapat Bonus","Tidak Mendapat Bonus") -> Tidak Mendapat Bonus | H13: =IF(G13="Mendapat Bonus",F13/(SUMIF($G$3:$G$375,"Mendapat Bonus",$F$3:$F$375)),0) -> 0 | I13: =IF(G13="Mendapat Bonus",H13*'Asumsi & Bobot'!$C$16,0) -> 0
A14: ='Vektor S & V'!J14 -> 136 | B14: ='Vektor S & V'!B14 -> HR Manager | C14: ='Data Mentah'!C14 -> Bachelor's | D14: ='Data Mentah'!E14 -> 18 | E14: ='Data Mentah'!F14 -> 140000 | F14: ='Vektor S & V'!I14 -> 0.0028441254 | G14: =IF(F14>='Asumsi & Bobot'!$C$15,"Mendapat Bonus","Tidak Mendapat Bonus") -> Tidak Mendapat Bonus | H14: =IF(G14="Mendapat Bonus",F14/(SUMIF($G$3:$G$375,"Mendapat Bonus",$F$3:$F$375)),0) -> 0 | I14: =IF(G14="Mendapat Bonus",H14*'Asumsi & Bobot'!$C$16,0) -> 0
... A375: ='Vektor S & V'!J375 -> 21 | B375: ='Vektor S & V'!B375 -> Senior Business Analyst | C375: ='Data Mentah'!C375 -> PhD | D375: ='Data Mentah'!E375 -> 15 | E375: ='Data Mentah'!F375 -> 150000 | F375: ='Vektor S & V'!I375 -> 0.0048024444 | G375: =IF(F375>='Asumsi & Bobot'!$C$15,"Mendapat Bonus","Tidak Mendapat Bonus") -> Mendapat Bonus | H375: =IF(G375="Mendapat Bonus",F375/(SUMIF($G$3:$G$375,"Mendapat Bonus",$F$3:$F$375)),0) -> 0.014530933 | I375: =IF(G375="Mendapat Bonus",H375*'Asumsi & Bobot'!$C$16,0) -> 726.54667
A376: TOTAL | G376: =COUNTIF($G$3:$G$375,"Mendapat Bonus")&" karyawan" -> 72 karyawan | I376: =SUM(I3:I375) -> 50000

Sheet Rangkuman
A1: RANGKUMAN HASIL SPK
A3: Indikator | B3: Nilai | C3: Format
A4: Total Karyawan Dievaluasi | B4: =COUNTA('Data Mentah'!A3:A375) -> 373 | C4: 0
A5: Karyawan Penerima Bonus | B5: =COUNTIF('Hasil & Bonus'!$G$3:$G$375,"Mendapat Bonus") -> 72 | C5: 0
A6: Total Anggaran Bonus ($) | B6: ='Asumsi & Bobot'!C16 -> 50000 | C6: $#,##0
A7: Total Bonus Dibagikan ($) | B7: =SUM('Hasil & Bonus'!I3:I375) -> 50000 | C7: $#,##0
A8: Bonus Tertinggi ($) | B8: =MAX('Hasil & Bonus'!I3:I375) -> 844.47435 | C8: $#,##0
A9: Bonus Terendah (penerima) | B9: =IFERROR(_xludf.aggregate(5,6,('Hasil & Bonus'!I3:I375)*('Hasil & Bonus'!G3:G375="Mendapat Bonus")),0) -> 0 | C9: $#,##0
A10: Skor V Tertinggi | B10: =MAX('Vektor S & V'!I3:I375) -> 0.0055819416 | C10: 0.000000
A11: Ambang Batas V | B11: ='Asumsi & Bobot'!C15 -> 0.004 | C11: 0.00000
A14: TOP 10 PENERIMA BONUS TERTINGGI
A15: Jabatan | B15: Vektor V | C15: Bonus ($)
A16: =IFERROR(INDEX('Hasil & Bonus'!$B$3:$B$375,MATCH(1,'Hasil & Bonus'!$A$3:$A$375,0)),"—") -> Director of Human Resources | B16: =IFERROR(INDEX('Hasil & Bonus'!$F$3:$F$375,MATCH(1,'Hasil & Bonus'!$A$3:$A$375,0)),"") -> 0.0055819416 | C16: =IFERROR(INDEX('Hasil & Bonus'!$I$3:$I$375,MATCH(1,'Hasil & Bonus'!$A$3:$A$375,0)),"") -> 844.47435
A17: =IFERROR(INDEX('Hasil & Bonus'!$B$3:$B$375,MATCH(2,'Hasil & Bonus'!$A$3:$A$375,0)),"—") -> Director of Sales and Marketing | B17: =IFERROR(INDEX('Hasil & Bonus'!$F$3:$F$375,MATCH(2,'Hasil & Bonus'!$A$3:$A$375,0)),"") -> 0.0054905999 | C17: =IFERROR(INDEX('Hasil & Bonus'!$I$3:$I$375,MATCH(2,'Hasil & Bonus'!$A$3:$A$375,0)),"") -> 830.65555
A18: =IFERROR(INDEX('Hasil & Bonus'!$B$3:$B$375,MATCH(3,'Hasil & Bonus'!$A$3:$A$375,0)),"—") -> — | B18: =IFERROR(INDEX('Hasil & Bonus'!$F$3:$F$375,MATCH(3,'Hasil & Bonus'!$A$3:$A$375,0)),"") | C18: =IFERROR(INDEX('Hasil & Bonus'!$I$3:$I$375,MATCH(3,'Hasil & Bonus'!$A$3:$A$375,0)),"")
A19: =IFERROR(INDEX('Hasil & Bonus'!$B$3:$B$375,MATCH(4,'Hasil & Bonus'!$A$3:$A$375,0)),"—") -> — | B19: =IFERROR(INDEX('Hasil & Bonus'!$F$3:$F$375,MATCH(4,'Hasil & Bonus'!$A$3:$A$375,0)),"") | C19: =IFERROR(INDEX('Hasil & Bonus'!$I$3:$I$375,MATCH(4,'Hasil & Bonus'!$A$3:$A$375,0)),"")
A20: =IFERROR(INDEX('Hasil & Bonus'!$B$3:$B$375,MATCH(5,'Hasil & Bonus'!$A$3:$A$375,0)),"—") -> Senior Product Designer | B20: =IFERROR(INDEX('Hasil & Bonus'!$F$3:$F$375,MATCH(5,'Hasil & Bonus'!$A$3:$A$375,0)),"") -> 0.00505535 | C20: =IFERROR(INDEX('Hasil & Bonus'!$I$3:$I$375,MATCH(5,'Hasil & Bonus'!$A$3:$A$375,0)),"") -> 764.80796
A21: =IFERROR(INDEX('Hasil & Bonus'!$B$3:$B$375,MATCH(6,'Hasil & Bonus'!$A$3:$A$375,0)),"—") -> Senior HR Manager | B21: =IFERROR(INDEX('Hasil & Bonus'!$F$3:$F$375,MATCH(6,'Hasil & Bonus'!$A$3:$A$375,0)),"") -> 0.0050218133 | C21: =IFERROR(INDEX('Hasil & Bonus'!$I$3:$I$375,MATCH(6,'Hasil & Bonus'!$A$3:$A$375,0)),"") -> 759.7343
A22: =IFERROR(INDEX('Hasil & Bonus'!$B$3:$B$375,MATCH(7,'Hasil & Bonus'!$A$3:$A$375,0)),"—") -> Senior Marketing Manager | B22: =IFERROR(INDEX('Hasil & Bonus'!$F$3:$F$375,MATCH(7,'Hasil & Bonus'!$A$3:$A$375,0)),"") -> 0.0050112559 | C22: =IFERROR(INDEX('Hasil & Bonus'!$I$3:$I$375,MATCH(7,'Hasil & Bonus'!$A$3:$A$375,0)),"") -> 758.1371
A23: =IFERROR(INDEX('Hasil & Bonus'!$B$3:$B$375,MATCH(8,'Hasil & Bonus'!$A$3:$A$375,0)),"—") -> Senior Marketing Manager | B23: =IFERROR(INDEX('Hasil & Bonus'!$F$3:$F$375,MATCH(8,'Hasil & Bonus'!$A$3:$A$375,0)),"") -> 0.0049583366 | C23: =IFERROR(INDEX('Hasil & Bonus'!$I$3:$I$375,MATCH(8,'Hasil & Bonus'!$A$3:$A$375,0)),"") -> 750.13111
A24: =IFERROR(INDEX('Hasil & Bonus'!$B$3:$B$375,MATCH(9,'Hasil & Bonus'!$A$3:$A$375,0)),"—") -> Senior Scientist | B24: =IFERROR(INDEX('Hasil & Bonus'!$F$3:$F$375,MATCH(9,'Hasil & Bonus'!$A$3:$A$375,0)),"") -> 0.0049288381 | C24: =IFERROR(INDEX('Hasil & Bonus'!$I$3:$I$375,MATCH(9,'Hasil & Bonus'!$A$3:$A$375,0)),"") -> 745.66838
A25: =IFERROR(INDEX('Hasil & Bonus'!$B$3:$B$375,MATCH(10,'Hasil & Bonus'!$A$3:$A$375,0)),"—") -> Senior UX Designer | B25: =IFERROR(INDEX('Hasil & Bonus'!$F$3:$F$375,MATCH(10,'Hasil & Bonus'!$A$3:$A$375,0)),"") -> 0.0048944858 | C25: =IFERROR(INDEX('Hasil & Bonus'!$I$3:$I$375,MATCH(10,'Hasil & Bonus'!$A$3:$A$375,0)),"") -> 740.47133
